cmu/__init__.py
cmu/config_parser.py
cmu/distributed.py
cmu/history_buffer.py
cmu/logger.py
cmu/lr_scheduler.py
cmu/misc.py
cmu/trainer.py
cmu/hooks/__init__.py
cmu/hooks/checkpoint_hook.py
cmu/hooks/distributed_hook.py
cmu/hooks/eval_hook.py
cmu/hooks/hookbase.py
cmu/hooks/logger_hook.py
cmu/hooks/lr_update_hook.py
core_ml_utils-1.0.0.data/data/requirements.txt
core_ml_utils-1.0.0.dist-info/LICENSE
core_ml_utils-1.0.0.dist-info/METADATA
core_ml_utils-1.0.0.dist-info/WHEEL
core_ml_utils-1.0.0.dist-info/top_level.txt
core_ml_utils-1.0.0.dist-info/RECORD
